ataacona/__init__.py
ataacona/ataacona.py
ataacona/common.py
ataacona-0.0.1.dist-info/licenses/LICENSE
ataacona-0.0.1.dist-info/METADATA
ataacona-0.0.1.dist-info/WHEEL
ataacona-0.0.1.dist-info/entry_points.txt
ataacona-0.0.1.dist-info/top_level.txt
ataacona-0.0.1.dist-info/RECORD
